x12/__init__.py
x12/common/__init__.py
x12/common/colors.py
x12/parser/__init__.py
x12/parser/analyze.py
x12/parser/context.py
x12/parser/loop.py
x12/parser/parse.py
x12/parser/segment.py
x12/schema/__init__.py
x12/schema/schema.py
spaceavocado_x12-1.0.1.dist-info/LICENSE.md
spaceavocado_x12-1.0.1.dist-info/METADATA
spaceavocado_x12-1.0.1.dist-info/WHEEL
spaceavocado_x12-1.0.1.dist-info/top_level.txt
spaceavocado_x12-1.0.1.dist-info/RECORD
