Metadata-Version: 2.1
Name: spaceavocado-x12
Version: 1.0.1
Summary: Simple X12 files parser.
Author-email: David Horak <info@davidhorak.com>
License: Copyright (c) 2023, David Horak (info@davidhorak.com)
Project-URL: repository, https://github.com/spaceavocado/x12
Keywords: x12,parser,schema
Classifier: Development Status :: 4 - Beta
Classifier: Topic :: Utilities
Classifier: Programming Language :: Python
Classifier: Programming Language :: Python :: 3
Classifier: License :: OSI Approved :: MIT License
Requires-Python: >=3.7
License-File: LICENSE.md
